{
  "project_info": {
    "project_number": "1013717852044",
    "firebase_url": "https://collage-8c283-default-rtdb.firebaseio.com",
    "project_id": "collage-8c283",
    "storage_bucket": "collage-8c283.firebasestorage.app"
  },
  "client": [
    {
      "client_info": {
        "mobilesdk_app_id": "1:1013717852044:android:89aa6035beefd581ad40a9",
        "android_client_info": {
          "package_name": "com.example.yo"
        }
      },
      "oauth_client": [],
      "api_key": [
        {
          "current_key": "AIzaSyB2ROne_kHDI4BaozF2uz4TQNL_XN-xOvU"
        }
      ],
      "services": {
        "appinvite_service": {
          "other_platform_oauth_client": []
        }
      }
    }
  ],
  "configuration_version": "1"
}